MANIFEST.in
README.rst
setup.py
itemize/__init__.py
itemize/__main__.py
itemize/document.py
itemize/main.py
itemize.egg-info/PKG-INFO
itemize.egg-info/SOURCES.txt
itemize.egg-info/dependency_links.txt
itemize.egg-info/entry_points.txt
itemize.egg-info/requires.txt
itemize.egg-info/top_level.txt
itemize/templates/example/logo.png
itemize/templates/example/template.rml.jinja2
itemize/templates/receipt/base.rml.jinja2
itemize/templates/receipt/form.rml.jinja2
itemize/templates/receipt/graphics.rml.jinja2
itemize/templates/receipt/template.rml.jinja2
itemize/templates/receipt/images/amex.png
itemize/templates/receipt/images/diners_club.png
itemize/templates/receipt/images/discover.png
itemize/templates/receipt/images/generic.png
itemize/templates/receipt/images/jcb.png
itemize/templates/receipt/images/mastercard.png
itemize/templates/receipt/images/notice.png
itemize/templates/receipt/images/visa.png